mars/__init__.py
mars/cicai_configs.py
mars/mars_pipeline.py
mars/data/mars_datamanager.py
mars/data/mars_dataset.py
mars/data/mars_kitti_dataparser.py
mars/data/mars_vkitti_dataparser.py
mars/fields/car_nerf_field.py
mars/fields/nerfacto_field.py
mars/fields/vanilla_nerf_field.py
mars/model_components/losses.py
mars/models/car_nerf.py
mars/models/mipnerf.py
mars/models/nerfacto.py
mars/models/scene_graph.py
mars/models/semantic_nerfw.py
mars/models/sky_model.py
mars/models/vanilla_nerf.py
mars/process_data/generate_instance_mask_kitti_mot.py
mars/utils/neural_scene_graph_helper.py
mars_nerfstudio-0.3.4.dist-info/LICENSE
mars_nerfstudio-0.3.4.dist-info/METADATA
mars_nerfstudio-0.3.4.dist-info/WHEEL
mars_nerfstudio-0.3.4.dist-info/entry_points.txt
mars_nerfstudio-0.3.4.dist-info/top_level.txt
mars_nerfstudio-0.3.4.dist-info/RECORD
