Metadata-Version: 2.1
Name: mars-nerfstudio
Version: 0.3.4
Summary: The official code repository for the paper: MARS: An Instance-aware, Modular and Realistic Simulator for Autonomous Driving
License: Apache 2.0
Project-URL: Homeage, https://open-air-sun.github.io/mars
Classifier: Development Status :: 3 - Alpha
Classifier: Programming Language :: Python
Requires-Python: >=3.8.0
License-File: LICENSE
Requires-Dist: nerfstudio ==0.3.4
Requires-Dist: torchtyping
Requires-Dist: torch <2.1.0
Requires-Dist: tyro ==0.6.0
